[
  {
    "filename": "MDT (Medtronic plc.)  (10-K) 2025-06-20.txt",
    "chunk_index": 0
  },
  {
    "filename": "MDT (Medtronic plc.)  (10-K) 2025-06-20.txt",
    "chunk_index": 1
  },
  {
    "filename": "MDT (Medtronic plc.)  (10-K) 2025-06-20.txt",
    "chunk_index": 2
  },
  {
    "filename": "MDT (Medtronic plc.)  (10-K) 2025-06-20.txt",
    "chunk_index": 3
  },
  {
    "filename": "MDT (Medtronic plc.)  (10-K) 2025-06-20.txt",
    "chunk_index": 4
  },
  {
    "filename": "MDT (Medtronic plc.)  (10-K) 2025-06-20.txt",
    "chunk_index": 5
  },
  {
    "filename": "MDT (Medtronic plc.)  (10-K) 2025-06-20.txt",
    "chunk_index": 6
  },
  {
    "filename": "MDT (Medtronic plc.)  (10-K) 2025-06-20.txt",
    "chunk_index": 7
  },
  {
    "filename": "MDT (Medtronic plc.)  (10-K) 2025-06-20.txt",
    "chunk_index": 8
  },
  {
    "filename": "MDT (Medtronic plc.)  (10-K) 2025-06-20.txt",
    "chunk_index": 9
  },
  {
    "filename": "MDT (Medtronic plc.)  (10-K) 2025-06-20.txt",
    "chunk_index": 10
  },
  {
    "filename": "MDT (Medtronic plc.)  (10-K) 2025-06-20.txt",
    "chunk_index": 11
  },
  {
    "filename": "MDT (Medtronic plc.)  (10-K) 2025-06-20.txt",
    "chunk_index": 12
  },
  {
    "filename": "MDT (Medtronic plc.)  (10-K) 2025-06-20.txt",
    "chunk_index": 13
  },
  {
    "filename": "MDT (Medtronic plc.)  (10-K) 2025-06-20.txt",
    "chunk_index": 14
  },
  {
    "filename": "MDT (Medtronic plc.)  (10-K) 2025-06-20.txt",
    "chunk_index": 15
  },
  {
    "filename": "MDT (Medtronic plc.)  (10-K) 2025-06-20.txt",
    "chunk_index": 16
  },
  {
    "filename": "MDT (Medtronic plc.)  (10-K) 2025-06-20.txt",
    "chunk_index": 17
  },
  {
    "filename": "MDT (Medtronic plc.)  (10-K) 2025-06-20.txt",
    "chunk_index": 18
  },
  {
    "filename": "MDT (Medtronic plc.)  (10-K) 2025-06-20.txt",
    "chunk_index": 19
  },
  {
    "filename": "MDT (Medtronic plc.)  (10-K) 2025-06-20.txt",
    "chunk_index": 20
  },
  {
    "filename": "MDT (Medtronic plc.)  (10-K) 2025-06-20.txt",
    "chunk_index": 21
  },
  {
    "filename": "MDT (Medtronic plc.)  (10-K) 2025-06-20.txt",
    "chunk_index": 22
  },
  {
    "filename": "MDT (Medtronic plc.)  (10-K) 2025-06-20.txt",
    "chunk_index": 23
  },
  {
    "filename": "MDT (Medtronic plc.)  (10-K) 2025-06-20.txt",
    "chunk_index": 24
  },
  {
    "filename": "MDT (Medtronic plc.)  (10-K) 2025-06-20.txt",
    "chunk_index": 25
  },
  {
    "filename": "MDT (Medtronic plc.)  (10-K) 2025-06-20.txt",
    "chunk_index": 26
  },
  {
    "filename": "MDT (Medtronic plc.)  (10-K) 2025-06-20.txt",
    "chunk_index": 27
  },
  {
    "filename": "MDT (Medtronic plc.)  (10-K) 2025-06-20.txt",
    "chunk_index": 28
  },
  {
    "filename": "MDT (Medtronic plc.)  (10-K) 2025-06-20.txt",
    "chunk_index": 29
  },
  {
    "filename": "MDT (Medtronic plc.)  (10-K) 2025-06-20.txt",
    "chunk_index": 30
  },
  {
    "filename": "MDT (Medtronic plc.)  (10-K) 2025-06-20.txt",
    "chunk_index": 31
  },
  {
    "filename": "MDT (Medtronic plc.)  (10-K) 2025-06-20.txt",
    "chunk_index": 32
  },
  {
    "filename": "MDT (Medtronic plc.)  (10-K) 2025-06-20.txt",
    "chunk_index": 33
  },
  {
    "filename": "MDT (Medtronic plc.)  (10-K) 2025-06-20.txt",
    "chunk_index": 34
  },
  {
    "filename": "MDT (Medtronic plc.)  (10-K) 2025-06-20.txt",
    "chunk_index": 35
  },
  {
    "filename": "MDT (Medtronic plc.)  (10-K) 2025-06-20.txt",
    "chunk_index": 36
  },
  {
    "filename": "MDT (Medtronic plc.)  (10-K) 2025-06-20.txt",
    "chunk_index": 37
  },
  {
    "filename": "MDT (Medtronic plc.)  (10-K) 2025-06-20.txt",
    "chunk_index": 38
  },
  {
    "filename": "MDT (Medtronic plc.)  (10-K) 2025-06-20.txt",
    "chunk_index": 39
  },
  {
    "filename": "MDT (Medtronic plc.)  (10-K) 2025-06-20.txt",
    "chunk_index": 40
  },
  {
    "filename": "MDT (Medtronic plc.)  (10-K) 2025-06-20.txt",
    "chunk_index": 41
  },
  {
    "filename": "MDT (Medtronic plc.)  (10-K) 2025-06-20.txt",
    "chunk_index": 42
  },
  {
    "filename": "MDT (Medtronic plc.)  (10-K) 2025-06-20.txt",
    "chunk_index": 43
  },
  {
    "filename": "MDT (Medtronic plc.)  (10-K) 2025-06-20.txt",
    "chunk_index": 44
  },
  {
    "filename": "MDT (Medtronic plc.)  (10-K) 2025-06-20.txt",
    "chunk_index": 45
  },
  {
    "filename": "MDT (Medtronic plc.)  (10-K) 2025-06-20.txt",
    "chunk_index": 46
  },
  {
    "filename": "MDT (Medtronic plc.)  (10-K) 2025-06-20.txt",
    "chunk_index": 47
  },
  {
    "filename": "MDT (Medtronic plc.)  (10-K) 2025-06-20.txt",
    "chunk_index": 48
  },
  {
    "filename": "MDT (Medtronic plc.)  (10-K) 2025-06-20.txt",
    "chunk_index": 49
  },
  {
    "filename": "MDT (Medtronic plc.)  (10-K) 2025-06-20.txt",
    "chunk_index": 50
  },
  {
    "filename": "MDT (Medtronic plc.)  (10-K) 2025-06-20.txt",
    "chunk_index": 51
  },
  {
    "filename": "MDT (Medtronic plc.)  (10-K) 2025-06-20.txt",
    "chunk_index": 52
  },
  {
    "filename": "MDT (Medtronic plc.)  (10-K) 2025-06-20.txt",
    "chunk_index": 53
  },
  {
    "filename": "MDT (Medtronic plc.)  (10-K) 2025-06-20.txt",
    "chunk_index": 54
  },
  {
    "filename": "MDT (Medtronic plc.)  (10-K) 2025-06-20.txt",
    "chunk_index": 55
  },
  {
    "filename": "MDT (Medtronic plc.)  (10-K) 2025-06-20.txt",
    "chunk_index": 56
  },
  {
    "filename": "MDT (Medtronic plc.)  (10-K) 2025-06-20.txt",
    "chunk_index": 57
  },
  {
    "filename": "MDT (Medtronic plc.)  (10-K) 2025-06-20.txt",
    "chunk_index": 58
  },
  {
    "filename": "MDT (Medtronic plc.)  (10-K) 2025-06-20.txt",
    "chunk_index": 59
  },
  {
    "filename": "MDT (Medtronic plc.)  (10-K) 2025-06-20.txt",
    "chunk_index": 60
  },
  {
    "filename": "MDT (Medtronic plc.)  (10-K) 2025-06-20.txt",
    "chunk_index": 61
  },
  {
    "filename": "MDT (Medtronic plc.)  (10-K) 2025-06-20.txt",
    "chunk_index": 62
  },
  {
    "filename": "MDT (Medtronic plc.)  (10-K) 2025-06-20.txt",
    "chunk_index": 63
  },
  {
    "filename": "MDT (Medtronic plc.)  (10-K) 2025-06-20.txt",
    "chunk_index": 64
  },
  {
    "filename": "MDT (Medtronic plc.)  (10-K) 2025-06-20.txt",
    "chunk_index": 65
  },
  {
    "filename": "MDT (Medtronic plc.)  (10-K) 2025-06-20.txt",
    "chunk_index": 66
  },
  {
    "filename": "MDT (Medtronic plc.)  (10-K) 2025-06-20.txt",
    "chunk_index": 67
  },
  {
    "filename": "MDT (Medtronic plc.)  (10-K) 2025-06-20.txt",
    "chunk_index": 68
  },
  {
    "filename": "MDT (Medtronic plc.)  (10-K) 2025-06-20.txt",
    "chunk_index": 69
  },
  {
    "filename": "MDT (Medtronic plc.)  (10-K) 2025-06-20.txt",
    "chunk_index": 70
  },
  {
    "filename": "MDT (Medtronic plc.)  (10-K) 2025-06-20.txt",
    "chunk_index": 71
  },
  {
    "filename": "MDT (Medtronic plc.)  (10-K) 2025-06-20.txt",
    "chunk_index": 72
  },
  {
    "filename": "MDT (Medtronic plc.)  (10-K) 2025-06-20.txt",
    "chunk_index": 73
  },
  {
    "filename": "MDT (Medtronic plc.)  (10-K) 2025-06-20.txt",
    "chunk_index": 74
  },
  {
    "filename": "MDT (Medtronic plc.)  (10-K) 2025-06-20.txt",
    "chunk_index": 75
  },
  {
    "filename": "MDT (Medtronic plc.)  (10-K) 2025-06-20.txt",
    "chunk_index": 76
  },
  {
    "filename": "MDT (Medtronic plc.)  (10-K) 2025-06-20.txt",
    "chunk_index": 77
  },
  {
    "filename": "MDT (Medtronic plc.)  (10-K) 2025-06-20.txt",
    "chunk_index": 78
  },
  {
    "filename": "MDT (Medtronic plc.)  (10-K) 2025-06-20.txt",
    "chunk_index": 79
  },
  {
    "filename": "MDT (Medtronic plc.)  (10-K) 2025-06-20.txt",
    "chunk_index": 80
  },
  {
    "filename": "MDT (Medtronic plc.)  (10-K) 2025-06-20.txt",
    "chunk_index": 81
  },
  {
    "filename": "MDT (Medtronic plc.)  (10-K) 2025-06-20.txt",
    "chunk_index": 82
  },
  {
    "filename": "MDT (Medtronic plc.)  (10-K) 2025-06-20.txt",
    "chunk_index": 83
  },
  {
    "filename": "MDT (Medtronic plc.)  (10-K) 2025-06-20.txt",
    "chunk_index": 84
  },
  {
    "filename": "MDT (Medtronic plc.)  (10-K) 2025-06-20.txt",
    "chunk_index": 85
  },
  {
    "filename": "MDT (Medtronic plc.)  (10-K) 2025-06-20.txt",
    "chunk_index": 86
  },
  {
    "filename": "MDT (Medtronic plc.)  (10-K) 2025-06-20.txt",
    "chunk_index": 87
  },
  {
    "filename": "MDT (Medtronic plc.)  (10-K) 2025-06-20.txt",
    "chunk_index": 88
  },
  {
    "filename": "MDT (Medtronic plc.)  (10-K) 2025-06-20.txt",
    "chunk_index": 89
  },
  {
    "filename": "MDT (Medtronic plc.)  (10-K) 2025-06-20.txt",
    "chunk_index": 90
  },
  {
    "filename": "MDT (Medtronic plc.)  (10-K) 2025-06-20.txt",
    "chunk_index": 91
  },
  {
    "filename": "MDT (Medtronic plc.)  (10-K) 2025-06-20.txt",
    "chunk_index": 92
  },
  {
    "filename": "MDT (Medtronic plc.)  (10-K) 2025-06-20.txt",
    "chunk_index": 93
  },
  {
    "filename": "MDT (Medtronic plc.)  (10-K) 2025-06-20.txt",
    "chunk_index": 94
  },
  {
    "filename": "MDT (Medtronic plc.)  (10-K) 2025-06-20.txt",
    "chunk_index": 95
  },
  {
    "filename": "MDT (Medtronic plc.)  (10-K) 2025-06-20.txt",
    "chunk_index": 96
  },
  {
    "filename": "MDT (Medtronic plc.)  (10-K) 2025-06-20.txt",
    "chunk_index": 97
  },
  {
    "filename": "MDT (Medtronic plc.)  (10-K) 2025-06-20.txt",
    "chunk_index": 98
  },
  {
    "filename": "MDT (Medtronic plc.)  (10-K) 2025-06-20.txt",
    "chunk_index": 99
  },
  {
    "filename": "MDT (Medtronic plc.)  (10-K) 2025-06-20.txt",
    "chunk_index": 100
  },
  {
    "filename": "MDT (Medtronic plc.)  (10-K) 2025-06-20.txt",
    "chunk_index": 101
  },
  {
    "filename": "MDT (Medtronic plc.)  (10-K) 2025-06-20.txt",
    "chunk_index": 102
  },
  {
    "filename": "MDT (Medtronic plc.)  (10-K) 2025-06-20.txt",
    "chunk_index": 103
  },
  {
    "filename": "MDT (Medtronic plc.)  (10-K) 2025-06-20.txt",
    "chunk_index": 104
  },
  {
    "filename": "MDT (Medtronic plc.)  (10-K) 2025-06-20.txt",
    "chunk_index": 105
  },
  {
    "filename": "MDT (Medtronic plc.)  (10-K) 2025-06-20.txt",
    "chunk_index": 106
  },
  {
    "filename": "MDT (Medtronic plc.)  (10-K) 2025-06-20.txt",
    "chunk_index": 107
  },
  {
    "filename": "MDT (Medtronic plc.)  (10-K) 2025-06-20.txt",
    "chunk_index": 108
  },
  {
    "filename": "MDT (Medtronic plc.)  (10-K) 2025-06-20.txt",
    "chunk_index": 109
  },
  {
    "filename": "MDT (Medtronic plc.)  (10-K) 2025-06-20.txt",
    "chunk_index": 110
  },
  {
    "filename": "MDT (Medtronic plc.)  (10-K) 2025-06-20.txt",
    "chunk_index": 111
  },
  {
    "filename": "MDT (Medtronic plc.)  (10-K) 2025-06-20.txt",
    "chunk_index": 112
  },
  {
    "filename": "MDT (Medtronic plc.)  (10-K) 2025-06-20.txt",
    "chunk_index": 113
  },
  {
    "filename": "MDT (Medtronic plc.)  (10-K) 2025-06-20.txt",
    "chunk_index": 114
  },
  {
    "filename": "MDT (Medtronic plc.)  (10-K) 2025-06-20.txt",
    "chunk_index": 115
  },
  {
    "filename": "MDT (Medtronic plc.)  (10-K) 2025-06-20.txt",
    "chunk_index": 116
  },
  {
    "filename": "MDT (Medtronic plc.)  (10-K) 2025-06-20.txt",
    "chunk_index": 117
  },
  {
    "filename": "MDT (Medtronic plc.)  (10-K) 2025-06-20.txt",
    "chunk_index": 118
  },
  {
    "filename": "MDT (Medtronic plc.)  (10-K) 2025-06-20.txt",
    "chunk_index": 119
  },
  {
    "filename": "MDT (Medtronic plc.)  (10-K) 2025-06-20.txt",
    "chunk_index": 120
  },
  {
    "filename": "MDT (Medtronic plc.)  (10-K) 2025-06-20.txt",
    "chunk_index": 121
  },
  {
    "filename": "MDT (Medtronic plc.)  (10-K) 2025-06-20.txt",
    "chunk_index": 122
  },
  {
    "filename": "MDT (Medtronic plc.)  (10-K) 2025-06-20.txt",
    "chunk_index": 123
  },
  {
    "filename": "MDT (Medtronic plc.)  (10-K) 2025-06-20.txt",
    "chunk_index": 124
  },
  {
    "filename": "MDT (Medtronic plc.)  (10-K) 2025-06-20.txt",
    "chunk_index": 125
  },
  {
    "filename": "MDT (Medtronic plc.)  (10-K) 2025-06-20.txt",
    "chunk_index": 126
  },
  {
    "filename": "MDT (Medtronic plc.)  (10-K) 2025-06-20.txt",
    "chunk_index": 127
  },
  {
    "filename": "MDT (Medtronic plc.)  (10-K) 2025-06-20.txt",
    "chunk_index": 128
  },
  {
    "filename": "MDT (Medtronic plc.)  (10-K) 2025-06-20.txt",
    "chunk_index": 129
  },
  {
    "filename": "MDT (Medtronic plc.)  (10-K) 2025-06-20.txt",
    "chunk_index": 130
  },
  {
    "filename": "MDT (Medtronic plc.)  (10-K) 2025-06-20.txt",
    "chunk_index": 131
  },
  {
    "filename": "MDT (Medtronic plc.)  (10-K) 2025-06-20.txt",
    "chunk_index": 132
  },
  {
    "filename": "MDT (Medtronic plc.)  (10-K) 2025-06-20.txt",
    "chunk_index": 133
  },
  {
    "filename": "MDT (Medtronic plc.)  (10-K) 2025-06-20.txt",
    "chunk_index": 134
  },
  {
    "filename": "MDT (Medtronic plc.)  (10-K) 2025-06-20.txt",
    "chunk_index": 135
  },
  {
    "filename": "MDT (Medtronic plc.)  (10-K) 2025-06-20.txt",
    "chunk_index": 136
  },
  {
    "filename": "MDT (Medtronic plc.)  (10-K) 2025-06-20.txt",
    "chunk_index": 137
  },
  {
    "filename": "MDT (Medtronic plc.)  (10-K) 2025-06-20.txt",
    "chunk_index": 138
  },
  {
    "filename": "MDT (Medtronic plc.)  (10-K) 2025-06-20.txt",
    "chunk_index": 139
  },
  {
    "filename": "MDT (Medtronic plc.)  (10-K) 2025-06-20.txt",
    "chunk_index": 140
  },
  {
    "filename": "MDT (Medtronic plc.)  (10-K) 2025-06-20.txt",
    "chunk_index": 141
  },
  {
    "filename": "MDT (Medtronic plc.)  (10-K) 2025-06-20.txt",
    "chunk_index": 142
  },
  {
    "filename": "MDT (Medtronic plc.)  (10-K) 2025-06-20.txt",
    "chunk_index": 143
  },
  {
    "filename": "MDT (Medtronic plc.)  (10-K) 2025-06-20.txt",
    "chunk_index": 144
  },
  {
    "filename": "MDT (Medtronic plc.)  (10-K) 2025-06-20.txt",
    "chunk_index": 145
  },
  {
    "filename": "MDT (Medtronic plc.)  (10-K) 2025-06-20.txt",
    "chunk_index": 146
  },
  {
    "filename": "MDT (Medtronic plc.)  (10-K) 2025-06-20.txt",
    "chunk_index": 147
  },
  {
    "filename": "MDT (Medtronic plc.)  (10-K) 2025-06-20.txt",
    "chunk_index": 148
  },
  {
    "filename": "MDT (Medtronic plc.)  (10-K) 2025-06-20.txt",
    "chunk_index": 149
  },
  {
    "filename": "MDT (Medtronic plc.)  (10-K) 2025-06-20.txt",
    "chunk_index": 150
  },
  {
    "filename": "MDT (Medtronic plc.)  (10-K) 2025-06-20.txt",
    "chunk_index": 151
  },
  {
    "filename": "MDT (Medtronic plc.)  (10-K) 2025-06-20.txt",
    "chunk_index": 152
  },
  {
    "filename": "MDT (Medtronic plc.)  (10-K) 2025-06-20.txt",
    "chunk_index": 153
  },
  {
    "filename": "MDT (Medtronic plc.)  (10-K) 2025-06-20.txt",
    "chunk_index": 154
  },
  {
    "filename": "MDT (Medtronic plc.)  (10-K) 2025-06-20.txt",
    "chunk_index": 155
  },
  {
    "filename": "MDT (Medtronic plc.)  (10-K) 2025-06-20.txt",
    "chunk_index": 156
  },
  {
    "filename": "MDT (Medtronic plc.)  (10-K) 2025-06-20.txt",
    "chunk_index": 157
  },
  {
    "filename": "MDT (Medtronic plc.)  (10-K) 2025-06-20.txt",
    "chunk_index": 158
  },
  {
    "filename": "MDT (Medtronic plc.)  (10-K) 2025-06-20.txt",
    "chunk_index": 159
  },
  {
    "filename": "MDT (Medtronic plc.)  (10-K) 2025-06-20.txt",
    "chunk_index": 160
  },
  {
    "filename": "MDT (Medtronic plc.)  (10-K) 2025-06-20.txt",
    "chunk_index": 161
  },
  {
    "filename": "MDT (Medtronic plc.)  (10-K) 2025-06-20.txt",
    "chunk_index": 162
  },
  {
    "filename": "MDT (Medtronic plc.)  (10-K) 2025-06-20.txt",
    "chunk_index": 163
  },
  {
    "filename": "MDT (Medtronic plc.)  (10-K) 2025-06-20.txt",
    "chunk_index": 164
  },
  {
    "filename": "MDT (Medtronic plc.)  (10-K) 2025-06-20.txt",
    "chunk_index": 165
  },
  {
    "filename": "MDT (Medtronic plc.)  (10-K) 2025-06-20.txt",
    "chunk_index": 166
  },
  {
    "filename": "MDT (Medtronic plc.)  (10-K) 2025-06-20.txt",
    "chunk_index": 167
  },
  {
    "filename": "MDT (Medtronic plc.)  (10-K) 2025-06-20.txt",
    "chunk_index": 168
  },
  {
    "filename": "MDT (Medtronic plc.)  (10-K) 2025-06-20.txt",
    "chunk_index": 169
  },
  {
    "filename": "MDT (Medtronic plc.)  (10-K) 2025-06-20.txt",
    "chunk_index": 170
  },
  {
    "filename": "MDT (Medtronic plc.)  (10-K) 2025-06-20.txt",
    "chunk_index": 171
  },
  {
    "filename": "MDT (Medtronic plc.)  (10-K) 2025-06-20.txt",
    "chunk_index": 172
  },
  {
    "filename": "MDT (Medtronic plc.)  (10-K) 2025-06-20.txt",
    "chunk_index": 173
  },
  {
    "filename": "MDT (Medtronic plc.)  (10-K) 2025-06-20.txt",
    "chunk_index": 174
  },
  {
    "filename": "MDT (Medtronic plc.)  (10-K) 2025-06-20.txt",
    "chunk_index": 175
  },
  {
    "filename": "MDT (Medtronic plc.)  (10-K) 2025-06-20.txt",
    "chunk_index": 176
  },
  {
    "filename": "MDT (Medtronic plc.)  (10-K) 2025-06-20.txt",
    "chunk_index": 177
  },
  {
    "filename": "MDT (Medtronic plc.)  (10-K) 2025-06-20.txt",
    "chunk_index": 178
  },
  {
    "filename": "MDT (Medtronic plc.)  (10-K) 2025-06-20.txt",
    "chunk_index": 179
  },
  {
    "filename": "MDT (Medtronic plc.)  (10-K) 2025-06-20.txt",
    "chunk_index": 180
  },
  {
    "filename": "MDT (Medtronic plc.)  (10-K) 2025-06-20.txt",
    "chunk_index": 181
  },
  {
    "filename": "MDT (Medtronic plc.)  (10-K) 2025-06-20.txt",
    "chunk_index": 182
  },
  {
    "filename": "MDT (Medtronic plc.)  (10-K) 2025-06-20.txt",
    "chunk_index": 183
  },
  {
    "filename": "MDT (Medtronic plc.)  (10-K) 2025-06-20.txt",
    "chunk_index": 184
  },
  {
    "filename": "MDT (Medtronic plc.)  (10-K) 2025-06-20.txt",
    "chunk_index": 185
  },
  {
    "filename": "MDT (Medtronic plc.)  (10-K) 2025-06-20.txt",
    "chunk_index": 186
  },
  {
    "filename": "MDT (Medtronic plc.)  (10-K) 2025-06-20.txt",
    "chunk_index": 187
  },
  {
    "filename": "MDT (Medtronic plc.)  (10-K) 2025-06-20.txt",
    "chunk_index": 188
  },
  {
    "filename": "MDT (Medtronic plc.)  (10-K) 2025-06-20.txt",
    "chunk_index": 189
  },
  {
    "filename": "MDT (Medtronic plc.)  (10-K) 2025-06-20.txt",
    "chunk_index": 190
  },
  {
    "filename": "MDT (Medtronic plc.)  (10-K) 2025-06-20.txt",
    "chunk_index": 191
  },
  {
    "filename": "MDT (Medtronic plc.)  (10-K) 2025-06-20.txt",
    "chunk_index": 192
  },
  {
    "filename": "MDT (Medtronic plc.)  (10-K) 2025-06-20.txt",
    "chunk_index": 193
  },
  {
    "filename": "MDT (Medtronic plc.)  (10-K) 2025-06-20.txt",
    "chunk_index": 194
  },
  {
    "filename": "MDT (Medtronic plc.)  (10-K) 2025-06-20.txt",
    "chunk_index": 195
  },
  {
    "filename": "MDT (Medtronic plc.)  (10-K) 2025-06-20.txt",
    "chunk_index": 196
  },
  {
    "filename": "MDT (Medtronic plc.)  (10-K) 2025-06-20.txt",
    "chunk_index": 197
  },
  {
    "filename": "MDT (Medtronic plc.)  (10-K) 2025-06-20.txt",
    "chunk_index": 198
  },
  {
    "filename": "MDT (Medtronic plc.)  (10-K) 2025-06-20.txt",
    "chunk_index": 199
  },
  {
    "filename": "MDT (Medtronic plc.)  (10-K) 2025-06-20.txt",
    "chunk_index": 200
  },
  {
    "filename": "MDT (Medtronic plc.)  (10-K) 2025-06-20.txt",
    "chunk_index": 201
  },
  {
    "filename": "MDT (Medtronic plc.)  (10-K) 2025-06-20.txt",
    "chunk_index": 202
  },
  {
    "filename": "MDT (Medtronic plc.)  (10-K) 2025-06-20.txt",
    "chunk_index": 203
  },
  {
    "filename": "MDT (Medtronic plc.)  (10-K) 2025-06-20.txt",
    "chunk_index": 204
  },
  {
    "filename": "MDT (Medtronic plc.)  (10-K) 2025-06-20.txt",
    "chunk_index": 205
  },
  {
    "filename": "MDT (Medtronic plc.)  (10-K) 2025-06-20.txt",
    "chunk_index": 206
  },
  {
    "filename": "MDT (Medtronic plc.)  (10-K) 2025-06-20.txt",
    "chunk_index": 207
  },
  {
    "filename": "MDT (Medtronic plc.)  (10-K) 2025-06-20.txt",
    "chunk_index": 208
  },
  {
    "filename": "MDT (Medtronic plc.)  (10-K) 2025-06-20.txt",
    "chunk_index": 209
  },
  {
    "filename": "MDT (Medtronic plc.)  (10-K) 2025-06-20.txt",
    "chunk_index": 210
  },
  {
    "filename": "MDT (Medtronic plc.)  (10-K) 2025-06-20.txt",
    "chunk_index": 211
  },
  {
    "filename": "MDT (Medtronic plc.)  (10-K) 2025-06-20.txt",
    "chunk_index": 212
  },
  {
    "filename": "MDT (Medtronic plc.)  (10-K) 2025-06-20.txt",
    "chunk_index": 213
  },
  {
    "filename": "MDT (Medtronic plc.)  (10-K) 2025-06-20.txt",
    "chunk_index": 214
  },
  {
    "filename": "MDT (Medtronic plc.)  (10-K) 2025-06-20.txt",
    "chunk_index": 215
  },
  {
    "filename": "MDT (Medtronic plc.)  (10-K) 2025-06-20.txt",
    "chunk_index": 216
  },
  {
    "filename": "MDT (Medtronic plc.)  (10-K) 2025-06-20.txt",
    "chunk_index": 217
  },
  {
    "filename": "MDT (Medtronic plc.)  (10-K) 2025-06-20.txt",
    "chunk_index": 218
  },
  {
    "filename": "MDT (Medtronic plc.)  (10-K) 2025-06-20.txt",
    "chunk_index": 219
  },
  {
    "filename": "MDT (Medtronic plc.)  (10-K) 2025-06-20.txt",
    "chunk_index": 220
  },
  {
    "filename": "MDT (Medtronic plc.)  (10-K) 2025-06-20.txt",
    "chunk_index": 221
  },
  {
    "filename": "MEDTRONIC PLC_10K_2024 ARS.txt",
    "chunk_index": 0
  },
  {
    "filename": "MEDTRONIC PLC_10K_2024 ARS.txt",
    "chunk_index": 1
  },
  {
    "filename": "MEDTRONIC PLC_10K_2024 ARS.txt",
    "chunk_index": 2
  },
  {
    "filename": "MEDTRONIC PLC_10K_2024 ARS.txt",
    "chunk_index": 3
  },
  {
    "filename": "MEDTRONIC PLC_10K_2024 ARS.txt",
    "chunk_index": 4
  },
  {
    "filename": "MEDTRONIC PLC_10K_2024 ARS.txt",
    "chunk_index": 5
  },
  {
    "filename": "MEDTRONIC PLC_10K_2024 ARS.txt",
    "chunk_index": 6
  },
  {
    "filename": "MEDTRONIC PLC_10K_2024 ARS.txt",
    "chunk_index": 7
  },
  {
    "filename": "MEDTRONIC PLC_10K_2024 ARS.txt",
    "chunk_index": 8
  },
  {
    "filename": "MEDTRONIC PLC_10K_2024 ARS.txt",
    "chunk_index": 9
  },
  {
    "filename": "MEDTRONIC PLC_10K_2024 ARS.txt",
    "chunk_index": 10
  },
  {
    "filename": "MEDTRONIC PLC_10K_2024 ARS.txt",
    "chunk_index": 11
  },
  {
    "filename": "MEDTRONIC PLC_10K_2024 ARS.txt",
    "chunk_index": 12
  },
  {
    "filename": "MEDTRONIC PLC_10K_2024 ARS.txt",
    "chunk_index": 13
  },
  {
    "filename": "MEDTRONIC PLC_10K_2024 ARS.txt",
    "chunk_index": 14
  },
  {
    "filename": "MEDTRONIC PLC_10K_2024 ARS.txt",
    "chunk_index": 15
  },
  {
    "filename": "MEDTRONIC PLC_10K_2024 ARS.txt",
    "chunk_index": 16
  },
  {
    "filename": "MEDTRONIC PLC_10K_2024 ARS.txt",
    "chunk_index": 17
  },
  {
    "filename": "MEDTRONIC PLC_10K_2024 ARS.txt",
    "chunk_index": 18
  },
  {
    "filename": "MEDTRONIC PLC_10K_2024 ARS.txt",
    "chunk_index": 19
  },
  {
    "filename": "MEDTRONIC PLC_10K_2024 ARS.txt",
    "chunk_index": 20
  },
  {
    "filename": "MEDTRONIC PLC_10K_2024 ARS.txt",
    "chunk_index": 21
  },
  {
    "filename": "MEDTRONIC PLC_10K_2024 ARS.txt",
    "chunk_index": 22
  },
  {
    "filename": "MEDTRONIC PLC_10K_2024 ARS.txt",
    "chunk_index": 23
  },
  {
    "filename": "MEDTRONIC PLC_10K_2024 ARS.txt",
    "chunk_index": 24
  },
  {
    "filename": "MEDTRONIC PLC_10K_2024 ARS.txt",
    "chunk_index": 25
  },
  {
    "filename": "MEDTRONIC PLC_10K_2024 ARS.txt",
    "chunk_index": 26
  },
  {
    "filename": "MEDTRONIC PLC_10K_2024 ARS.txt",
    "chunk_index": 27
  },
  {
    "filename": "MEDTRONIC PLC_10K_2024 ARS.txt",
    "chunk_index": 28
  },
  {
    "filename": "MEDTRONIC PLC_10K_2024 ARS.txt",
    "chunk_index": 29
  },
  {
    "filename": "MEDTRONIC PLC_10K_2024 ARS.txt",
    "chunk_index": 30
  },
  {
    "filename": "MEDTRONIC PLC_10K_2024 ARS.txt",
    "chunk_index": 31
  },
  {
    "filename": "MEDTRONIC PLC_10K_2024 ARS.txt",
    "chunk_index": 32
  },
  {
    "filename": "MEDTRONIC PLC_10K_2024 ARS.txt",
    "chunk_index": 33
  },
  {
    "filename": "MEDTRONIC PLC_10K_2024 ARS.txt",
    "chunk_index": 34
  },
  {
    "filename": "MEDTRONIC PLC_10K_2024 ARS.txt",
    "chunk_index": 35
  },
  {
    "filename": "MEDTRONIC PLC_10K_2024 ARS.txt",
    "chunk_index": 36
  },
  {
    "filename": "MEDTRONIC PLC_10K_2024 ARS.txt",
    "chunk_index": 37
  },
  {
    "filename": "MEDTRONIC PLC_10K_2024 ARS.txt",
    "chunk_index": 38
  },
  {
    "filename": "MEDTRONIC PLC_10K_2024 ARS.txt",
    "chunk_index": 39
  },
  {
    "filename": "MEDTRONIC PLC_10K_2024 ARS.txt",
    "chunk_index": 40
  },
  {
    "filename": "MEDTRONIC PLC_10K_2024 ARS.txt",
    "chunk_index": 41
  },
  {
    "filename": "MEDTRONIC PLC_10K_2024 ARS.txt",
    "chunk_index": 42
  },
  {
    "filename": "MEDTRONIC PLC_10K_2024 ARS.txt",
    "chunk_index": 43
  },
  {
    "filename": "MEDTRONIC PLC_10K_2024 ARS.txt",
    "chunk_index": 44
  },
  {
    "filename": "MEDTRONIC PLC_10K_2024 ARS.txt",
    "chunk_index": 45
  },
  {
    "filename": "MEDTRONIC PLC_10K_2024 ARS.txt",
    "chunk_index": 46
  },
  {
    "filename": "MEDTRONIC PLC_10K_2024 ARS.txt",
    "chunk_index": 47
  },
  {
    "filename": "MEDTRONIC PLC_10K_2024 ARS.txt",
    "chunk_index": 48
  },
  {
    "filename": "MEDTRONIC PLC_10K_2024 ARS.txt",
    "chunk_index": 49
  },
  {
    "filename": "MEDTRONIC PLC_10K_2024 ARS.txt",
    "chunk_index": 50
  },
  {
    "filename": "MEDTRONIC PLC_10K_2024 ARS.txt",
    "chunk_index": 51
  },
  {
    "filename": "MEDTRONIC PLC_10K_2024 ARS.txt",
    "chunk_index": 52
  },
  {
    "filename": "MEDTRONIC PLC_10K_2024 ARS.txt",
    "chunk_index": 53
  },
  {
    "filename": "MEDTRONIC PLC_10K_2024 ARS.txt",
    "chunk_index": 54
  },
  {
    "filename": "MEDTRONIC PLC_10K_2024 ARS.txt",
    "chunk_index": 55
  },
  {
    "filename": "MEDTRONIC PLC_10K_2024 ARS.txt",
    "chunk_index": 56
  },
  {
    "filename": "MEDTRONIC PLC_10K_2024 ARS.txt",
    "chunk_index": 57
  },
  {
    "filename": "MEDTRONIC PLC_10K_2024 ARS.txt",
    "chunk_index": 58
  },
  {
    "filename": "MEDTRONIC PLC_10K_2024 ARS.txt",
    "chunk_index": 59
  },
  {
    "filename": "MEDTRONIC PLC_10K_2024 ARS.txt",
    "chunk_index": 60
  },
  {
    "filename": "MEDTRONIC PLC_10K_2024 ARS.txt",
    "chunk_index": 61
  },
  {
    "filename": "MEDTRONIC PLC_10K_2024 ARS.txt",
    "chunk_index": 62
  },
  {
    "filename": "MEDTRONIC PLC_10K_2024 ARS.txt",
    "chunk_index": 63
  },
  {
    "filename": "MEDTRONIC PLC_10K_2024 ARS.txt",
    "chunk_index": 64
  },
  {
    "filename": "MEDTRONIC PLC_10K_2024 ARS.txt",
    "chunk_index": 65
  },
  {
    "filename": "MEDTRONIC PLC_10K_2024 ARS.txt",
    "chunk_index": 66
  },
  {
    "filename": "MEDTRONIC PLC_10K_2024 ARS.txt",
    "chunk_index": 67
  },
  {
    "filename": "MEDTRONIC PLC_10K_2024 ARS.txt",
    "chunk_index": 68
  },
  {
    "filename": "MEDTRONIC PLC_10K_2024 ARS.txt",
    "chunk_index": 69
  },
  {
    "filename": "MEDTRONIC PLC_10K_2024 ARS.txt",
    "chunk_index": 70
  },
  {
    "filename": "MEDTRONIC PLC_10K_2024 ARS.txt",
    "chunk_index": 71
  },
  {
    "filename": "MEDTRONIC PLC_10K_2024 ARS.txt",
    "chunk_index": 72
  },
  {
    "filename": "MEDTRONIC PLC_10K_2024 ARS.txt",
    "chunk_index": 73
  },
  {
    "filename": "MEDTRONIC PLC_10K_2024 ARS.txt",
    "chunk_index": 74
  },
  {
    "filename": "MEDTRONIC PLC_10K_2024 ARS.txt",
    "chunk_index": 75
  },
  {
    "filename": "MEDTRONIC PLC_10K_2024 ARS.txt",
    "chunk_index": 76
  },
  {
    "filename": "MEDTRONIC PLC_10K_2024 ARS.txt",
    "chunk_index": 77
  },
  {
    "filename": "MEDTRONIC PLC_10K_2024 ARS.txt",
    "chunk_index": 78
  },
  {
    "filename": "MEDTRONIC PLC_10K_2024 ARS.txt",
    "chunk_index": 79
  },
  {
    "filename": "MEDTRONIC PLC_10K_2024 ARS.txt",
    "chunk_index": 80
  },
  {
    "filename": "MEDTRONIC PLC_10K_2024 ARS.txt",
    "chunk_index": 81
  },
  {
    "filename": "MEDTRONIC PLC_10K_2024 ARS.txt",
    "chunk_index": 82
  },
  {
    "filename": "MEDTRONIC PLC_10K_2024 ARS.txt",
    "chunk_index": 83
  },
  {
    "filename": "MEDTRONIC PLC_10K_2024 ARS.txt",
    "chunk_index": 84
  },
  {
    "filename": "MEDTRONIC PLC_10K_2024 ARS.txt",
    "chunk_index": 85
  },
  {
    "filename": "MEDTRONIC PLC_10K_2024 ARS.txt",
    "chunk_index": 86
  },
  {
    "filename": "MEDTRONIC PLC_10K_2024 ARS.txt",
    "chunk_index": 87
  },
  {
    "filename": "MEDTRONIC PLC_10K_2024 ARS.txt",
    "chunk_index": 88
  },
  {
    "filename": "MEDTRONIC PLC_10K_2024 ARS.txt",
    "chunk_index": 89
  },
  {
    "filename": "MEDTRONIC PLC_10K_2024 ARS.txt",
    "chunk_index": 90
  },
  {
    "filename": "MEDTRONIC PLC_10K_2024 ARS.txt",
    "chunk_index": 91
  },
  {
    "filename": "MEDTRONIC PLC_10K_2024 ARS.txt",
    "chunk_index": 92
  },
  {
    "filename": "MEDTRONIC PLC_10K_2024 ARS.txt",
    "chunk_index": 93
  },
  {
    "filename": "MEDTRONIC PLC_10K_2024 ARS.txt",
    "chunk_index": 94
  },
  {
    "filename": "MEDTRONIC PLC_10K_2024 ARS.txt",
    "chunk_index": 95
  },
  {
    "filename": "MEDTRONIC PLC_10K_2024 ARS.txt",
    "chunk_index": 96
  },
  {
    "filename": "MEDTRONIC PLC_10K_2024 ARS.txt",
    "chunk_index": 97
  },
  {
    "filename": "MEDTRONIC PLC_10K_2024 ARS.txt",
    "chunk_index": 98
  },
  {
    "filename": "MEDTRONIC PLC_10K_2024 ARS.txt",
    "chunk_index": 99
  },
  {
    "filename": "MEDTRONIC PLC_10K_2024 ARS.txt",
    "chunk_index": 100
  },
  {
    "filename": "MEDTRONIC PLC_10K_2024 ARS.txt",
    "chunk_index": 101
  },
  {
    "filename": "MEDTRONIC PLC_10K_2024 ARS.txt",
    "chunk_index": 102
  },
  {
    "filename": "MEDTRONIC PLC_10K_2024 ARS.txt",
    "chunk_index": 103
  },
  {
    "filename": "MEDTRONIC PLC_10K_2024 ARS.txt",
    "chunk_index": 104
  },
  {
    "filename": "MEDTRONIC PLC_10K_2024 ARS.txt",
    "chunk_index": 105
  },
  {
    "filename": "MEDTRONIC PLC_10K_2024 ARS.txt",
    "chunk_index": 106
  },
  {
    "filename": "MEDTRONIC PLC_10K_2024 ARS.txt",
    "chunk_index": 107
  },
  {
    "filename": "MEDTRONIC PLC_10K_2024 ARS.txt",
    "chunk_index": 108
  },
  {
    "filename": "MEDTRONIC PLC_10K_2024 ARS.txt",
    "chunk_index": 109
  },
  {
    "filename": "MEDTRONIC PLC_10K_2024 ARS.txt",
    "chunk_index": 110
  },
  {
    "filename": "MEDTRONIC PLC_10K_2024 ARS.txt",
    "chunk_index": 111
  },
  {
    "filename": "MEDTRONIC PLC_10K_2024 ARS.txt",
    "chunk_index": 112
  },
  {
    "filename": "MEDTRONIC PLC_10K_2024 ARS.txt",
    "chunk_index": 113
  },
  {
    "filename": "MEDTRONIC PLC_10K_2024 ARS.txt",
    "chunk_index": 114
  },
  {
    "filename": "MEDTRONIC PLC_10K_2024 ARS.txt",
    "chunk_index": 115
  },
  {
    "filename": "MEDTRONIC PLC_10K_2024 ARS.txt",
    "chunk_index": 116
  },
  {
    "filename": "MEDTRONIC PLC_10K_2024 ARS.txt",
    "chunk_index": 117
  },
  {
    "filename": "MEDTRONIC PLC_10K_2024 ARS.txt",
    "chunk_index": 118
  },
  {
    "filename": "MEDTRONIC PLC_10K_2024 ARS.txt",
    "chunk_index": 119
  },
  {
    "filename": "MEDTRONIC PLC_10K_2024 ARS.txt",
    "chunk_index": 120
  },
  {
    "filename": "MEDTRONIC PLC_10K_2024 ARS.txt",
    "chunk_index": 121
  },
  {
    "filename": "MEDTRONIC PLC_10K_2024 ARS.txt",
    "chunk_index": 122
  },
  {
    "filename": "MEDTRONIC PLC_10K_2024 ARS.txt",
    "chunk_index": 123
  },
  {
    "filename": "MEDTRONIC PLC_10K_2024 ARS.txt",
    "chunk_index": 124
  },
  {
    "filename": "MEDTRONIC PLC_10K_2024 ARS.txt",
    "chunk_index": 125
  },
  {
    "filename": "MEDTRONIC PLC_10K_2024 ARS.txt",
    "chunk_index": 126
  },
  {
    "filename": "MEDTRONIC PLC_10K_2024 ARS.txt",
    "chunk_index": 127
  },
  {
    "filename": "MEDTRONIC PLC_10K_2024 ARS.txt",
    "chunk_index": 128
  },
  {
    "filename": "MEDTRONIC PLC_10K_2024 ARS.txt",
    "chunk_index": 129
  },
  {
    "filename": "MEDTRONIC PLC_10K_2024 ARS.txt",
    "chunk_index": 130
  },
  {
    "filename": "MEDTRONIC PLC_10K_2024 ARS.txt",
    "chunk_index": 131
  },
  {
    "filename": "MEDTRONIC PLC_10K_2024 ARS.txt",
    "chunk_index": 132
  },
  {
    "filename": "MEDTRONIC PLC_10K_2024 ARS.txt",
    "chunk_index": 133
  },
  {
    "filename": "MEDTRONIC PLC_10K_2024 ARS.txt",
    "chunk_index": 134
  },
  {
    "filename": "MEDTRONIC PLC_10K_2024 ARS.txt",
    "chunk_index": 135
  },
  {
    "filename": "MEDTRONIC PLC_10K_2024 ARS.txt",
    "chunk_index": 136
  },
  {
    "filename": "MEDTRONIC PLC_10K_2024 ARS.txt",
    "chunk_index": 137
  },
  {
    "filename": "MEDTRONIC PLC_10K_2024 ARS.txt",
    "chunk_index": 138
  },
  {
    "filename": "MEDTRONIC PLC_10K_2024 ARS.txt",
    "chunk_index": 139
  },
  {
    "filename": "MEDTRONIC PLC_10K_2024 ARS.txt",
    "chunk_index": 140
  },
  {
    "filename": "MEDTRONIC PLC_10K_2024 ARS.txt",
    "chunk_index": 141
  },
  {
    "filename": "MEDTRONIC PLC_10K_2024 ARS.txt",
    "chunk_index": 142
  },
  {
    "filename": "MEDTRONIC PLC_10K_2024 ARS.txt",
    "chunk_index": 143
  },
  {
    "filename": "MEDTRONIC PLC_10K_2024 ARS.txt",
    "chunk_index": 144
  }
]